{
  "metadata": {
    "timestamp": "2025-10-03T07:01:47.500395",
    "image_dimensions": {
      "width": 661,
      "height": 322
    },
    "num_objects": 9,
    "num_relations": 95,
    "num_grasps": 45
  },
  "nodes": [
    {
      "id": "obj_0",
      "label": "elongated_large_object",
      "semantic_category": "document",
      "confidence": 0.95,
      "semantic_confidence": 0.85,
      "bbox_2d": [
        15.0,
        108.0,
        645.0,
        213.0
      ],
      "bbox_3d": {
        "center": [
          337.5,
          214.5,
          1.0
        ],
        "dimensions": [
          0.645,
          0.213,
          0.1
        ],
        "min_bounds": [
          15.0,
          108.0,
          0.95
        ],
        "max_bounds": [
          660.0,
          321.0,
          1.05
        ]
      },
      "center_2d": [
        337.0,
        214.0
      ],
      "center_3d": [
        337.5,
        214.5,
        1.0
      ],
      "affordances": [
        "readable",
        "openable",
        "portable"
      ],
      "description": "printed publication",
      "num_grasps": 15,
      "best_grasp_quality": 0.6840211303259031,
      "graspable": true,
      "best_grasp": {
        "object_id": 3,
        "object_label": "elongated_large_object",
        "pose": {
          "position": [
            "0.047104254",
            "0.011698933",
            "0.5549001"
          ],
          "approach_vector": [
            0.5763708598541113,
            0.7933064309896235,
            -0.19611613513818407
          ],
          "rotation_matrix": "[[   -0.80902     0.58779           0]\n [   -0.58779    -0.80902           0]\n [          0           0           1]]",
          "angle": 3.7699111843077517,
          "quaternion": [
            1.0,
            0.0,
            0.0,
            0.0
          ]
        },
        "quality_score": 0.6840211303259031,
        "gripper_width": 0.08,
        "approach_vector": [
          0.5763708598541113,
          0.7933064309896235,
          -0.19611613513818407
        ],
        "grasp_center": [
          "0.018285714",
          "-0.02796639",
          "0.5647059"
        ],
        "confidence": 0.6498200738096078
      },
      "estimated_size": 1.0,
      "estimated_weight": "medium",
      "fragility": "moderate"
    },
    {
      "id": "obj_1",
      "label": "large_object",
      "semantic_category": "container",
      "confidence": 0.5,
      "semantic_confidence": 0.85,
      "bbox_2d": [
        0.0,
        0.0,
        223.0,
        321.0
      ],
      "bbox_3d": {
        "center": [
          111.5,
          160.5,
          1.0
        ],
        "dimensions": [
          0.223,
          0.321,
          0.1
        ],
        "min_bounds": [
          0.0,
          0.0,
          0.95
        ],
        "max_bounds": [
          223.0,
          321.0,
          1.05
        ]
      },
      "center_2d": [
        111.0,
        160.0
      ],
      "center_3d": [
        111.5,
        160.5,
        1.0
      ],
      "affordances": [
        "graspable",
        "holdable",
        "drinkable"
      ],
      "description": "drinking vessel",
      "num_grasps": 15,
      "best_grasp_quality": 0.6840211303259031,
      "graspable": true,
      "best_grasp": {
        "object_id": 3,
        "object_label": "large_object",
        "pose": {
          "position": [
            "0.3696589",
            "-0.21533374",
            "1.3156844"
          ],
          "approach_vector": [
            0.5763708598541113,
            0.7933064309896235,
            -0.19611613513818407
          ],
          "rotation_matrix": "[[   -0.80902     0.58779           0]\n [   -0.58779    -0.80902           0]\n [          0           0           1]]",
          "angle": 3.7699111843077517,
          "quaternion": [
            1.0,
            0.0,
            0.0,
            0.0
          ]
        },
        "quality_score": 0.6840211303259031,
        "gripper_width": 0.08,
        "approach_vector": [
          0.5763708598541113,
          0.7933064309896235,
          -0.19611613513818407
        ],
        "grasp_center": [
          "0.34084034",
          "-0.25499907",
          "1.3254902"
        ],
        "confidence": 0.6498200738096078
      },
      "estimated_size": 1.0,
      "estimated_weight": "medium",
      "fragility": "moderate"
    },
    {
      "id": "obj_2",
      "label": "large_object",
      "semantic_category": "container",
      "confidence": 0.6048590341348687,
      "semantic_confidence": 0.85,
      "bbox_2d": [
        171.0,
        122.0,
        192.0,
        199.0
      ],
      "bbox_3d": {
        "center": [
          267.0,
          221.5,
          1.0
        ],
        "dimensions": [
          0.192,
          0.199,
          0.1
        ],
        "min_bounds": [
          171.0,
          122.0,
          0.95
        ],
        "max_bounds": [
          363.0,
          321.0,
          1.05
        ]
      },
      "center_2d": [
        267.0,
        221.0
      ],
      "center_3d": [
        267.0,
        221.5,
        1.0
      ],
      "affordances": [
        "graspable",
        "holdable",
        "drinkable"
      ],
      "description": "drinking vessel",
      "num_grasps": 15,
      "best_grasp_quality": 0.6840211303259031,
      "graspable": true,
      "best_grasp": {
        "object_id": 3,
        "object_label": "large_object",
        "pose": {
          "position": [
            "0.3696589",
            "-0.21533374",
            "1.3156844"
          ],
          "approach_vector": [
            0.5763708598541113,
            0.7933064309896235,
            -0.19611613513818407
          ],
          "rotation_matrix": "[[   -0.80902     0.58779           0]\n [   -0.58779    -0.80902           0]\n [          0           0           1]]",
          "angle": 3.7699111843077517,
          "quaternion": [
            1.0,
            0.0,
            0.0,
            0.0
          ]
        },
        "quality_score": 0.6840211303259031,
        "gripper_width": 0.08,
        "approach_vector": [
          0.5763708598541113,
          0.7933064309896235,
          -0.19611613513818407
        ],
        "grasp_center": [
          "0.34084034",
          "-0.25499907",
          "1.3254902"
        ],
        "confidence": 0.6498200738096078
      },
      "estimated_size": 1.0,
      "estimated_weight": "medium",
      "fragility": "moderate"
    },
    {
      "id": "obj_3",
      "label": "elongated_large_object",
      "semantic_category": "document",
      "confidence": 0.95,
      "semantic_confidence": 0.85,
      "bbox_2d": [
        211.0,
        0.0,
        449.0,
        121.0
      ],
      "bbox_3d": {
        "center": [
          435.5,
          60.5,
          1.0
        ],
        "dimensions": [
          0.449,
          0.121,
          0.1
        ],
        "min_bounds": [
          211.0,
          0.0,
          0.95
        ],
        "max_bounds": [
          660.0,
          121.0,
          1.05
        ]
      },
      "center_2d": [
        435.0,
        60.0
      ],
      "center_3d": [
        435.5,
        60.5,
        1.0
      ],
      "affordances": [
        "readable",
        "openable",
        "portable"
      ],
      "description": "printed publication",
      "num_grasps": 15,
      "best_grasp_quality": 0.6840211303259031,
      "graspable": true,
      "best_grasp": {
        "object_id": 3,
        "object_label": "elongated_large_object",
        "pose": {
          "position": [
            "0.047104254",
            "0.011698933",
            "0.5549001"
          ],
          "approach_vector": [
            0.5763708598541113,
            0.7933064309896235,
            -0.19611613513818407
          ],
          "rotation_matrix": "[[   -0.80902     0.58779           0]\n [   -0.58779    -0.80902           0]\n [          0           0           1]]",
          "angle": 3.7699111843077517,
          "quaternion": [
            1.0,
            0.0,
            0.0,
            0.0
          ]
        },
        "quality_score": 0.6840211303259031,
        "gripper_width": 0.08,
        "approach_vector": [
          0.5763708598541113,
          0.7933064309896235,
          -0.19611613513818407
        ],
        "grasp_center": [
          "0.018285714",
          "-0.02796639",
          "0.5647059"
        ],
        "confidence": 0.6498200738096078
      },
      "estimated_size": 1.0,
      "estimated_weight": "medium",
      "fragility": "moderate"
    },
    {
      "id": "obj_4",
      "label": "small_object",
      "semantic_category": "electronics",
      "confidence": 0.514914391122177,
      "semantic_confidence": 0.85,
      "bbox_2d": [
        309.0,
        92.0,
        127.0,
        62.0
      ],
      "bbox_3d": {
        "center": [
          372.5,
          123.0,
          1.0
        ],
        "dimensions": [
          0.127,
          0.062,
          0.1
        ],
        "min_bounds": [
          309.0,
          92.0,
          0.95
        ],
        "max_bounds": [
          436.0,
          154.0,
          1.05
        ]
      },
      "center_2d": [
        372.0,
        123.0
      ],
      "center_3d": [
        372.5,
        123.0,
        1.0
      ],
      "affordances": [
        "usable",
        "pressable",
        "typing"
      ],
      "description": "computer input device",
      "num_grasps": 10,
      "best_grasp_quality": 0.4040490959842078,
      "graspable": true,
      "best_grasp": {
        "object_id": 3,
        "object_label": "small_object",
        "pose": {
          "position": [
            "-0.1907893",
            "-0.009275854",
            "0.64901775"
          ],
          "approach_vector": [
            0.5763708598541113,
            0.7933064309896235,
            -0.19611613513818407
          ],
          "rotation_matrix": "[[   -0.80902     0.58779           0]\n [   -0.58779    -0.80902           0]\n [          0           0           1]]",
          "angle": 3.7699111843077517,
          "quaternion": [
            1.0,
            0.0,
            0.0,
            0.0
          ]
        },
        "quality_score": 0.4040490959842078,
        "gripper_width": 0.08,
        "approach_vector": [
          0.5763708598541113,
          0.7933064309896235,
          -0.19611613513818407
        ],
        "grasp_center": [
          "-0.21960784",
          "-0.048941176",
          "0.65882355"
        ],
        "confidence": 0.25437770134791865
      },
      "estimated_size": 0.25631510416666664,
      "estimated_weight": "medium",
      "fragility": "moderate"
    },
    {
      "id": "obj_5",
      "label": "large_object",
      "semantic_category": "container",
      "confidence": 0.95,
      "semantic_confidence": 0.85,
      "bbox_2d": [
        250.0,
        0.0,
        410.0,
        279.0
      ],
      "bbox_3d": {
        "center": [
          455.0,
          139.5,
          1.0
        ],
        "dimensions": [
          0.41000000000000003,
          0.279,
          0.1
        ],
        "min_bounds": [
          250.0,
          0.0,
          0.95
        ],
        "max_bounds": [
          660.0,
          279.0,
          1.05
        ]
      },
      "center_2d": [
        455.0,
        139.0
      ],
      "center_3d": [
        455.0,
        139.5,
        1.0
      ],
      "affordances": [
        "graspable",
        "holdable",
        "drinkable"
      ],
      "description": "drinking vessel",
      "num_grasps": 15,
      "best_grasp_quality": 0.6840211303259031,
      "graspable": true,
      "best_grasp": {
        "object_id": 3,
        "object_label": "large_object",
        "pose": {
          "position": [
            "0.3696589",
            "-0.21533374",
            "1.3156844"
          ],
          "approach_vector": [
            0.5763708598541113,
            0.7933064309896235,
            -0.19611613513818407
          ],
          "rotation_matrix": "[[   -0.80902     0.58779           0]\n [   -0.58779    -0.80902           0]\n [          0           0           1]]",
          "angle": 3.7699111843077517,
          "quaternion": [
            1.0,
            0.0,
            0.0,
            0.0
          ]
        },
        "quality_score": 0.6840211303259031,
        "gripper_width": 0.08,
        "approach_vector": [
          0.5763708598541113,
          0.7933064309896235,
          -0.19611613513818407
        ],
        "grasp_center": [
          "0.34084034",
          "-0.25499907",
          "1.3254902"
        ],
        "confidence": 0.6498200738096078
      },
      "estimated_size": 1.0,
      "estimated_weight": "medium",
      "fragility": "moderate"
    },
    {
      "id": "obj_6",
      "label": "elongated_large_object",
      "semantic_category": "document",
      "confidence": 0.95,
      "semantic_confidence": 0.85,
      "bbox_2d": [
        178.0,
        116.0,
        482.0,
        128.0
      ],
      "bbox_3d": {
        "center": [
          419.0,
          180.0,
          1.0
        ],
        "dimensions": [
          0.482,
          0.128,
          0.1
        ],
        "min_bounds": [
          178.0,
          116.0,
          0.95
        ],
        "max_bounds": [
          660.0,
          244.0,
          1.05
        ]
      },
      "center_2d": [
        419.0,
        180.0
      ],
      "center_3d": [
        419.0,
        180.0,
        1.0
      ],
      "affordances": [
        "readable",
        "openable",
        "portable"
      ],
      "description": "printed publication",
      "num_grasps": 15,
      "best_grasp_quality": 0.6840211303259031,
      "graspable": true,
      "best_grasp": {
        "object_id": 3,
        "object_label": "elongated_large_object",
        "pose": {
          "position": [
            "0.047104254",
            "0.011698933",
            "0.5549001"
          ],
          "approach_vector": [
            0.5763708598541113,
            0.7933064309896235,
            -0.19611613513818407
          ],
          "rotation_matrix": "[[   -0.80902     0.58779           0]\n [   -0.58779    -0.80902           0]\n [          0           0           1]]",
          "angle": 3.7699111843077517,
          "quaternion": [
            1.0,
            0.0,
            0.0,
            0.0
          ]
        },
        "quality_score": 0.6840211303259031,
        "gripper_width": 0.08,
        "approach_vector": [
          0.5763708598541113,
          0.7933064309896235,
          -0.19611613513818407
        ],
        "grasp_center": [
          "0.018285714",
          "-0.02796639",
          "0.5647059"
        ],
        "confidence": 0.6498200738096078
      },
      "estimated_size": 1.0,
      "estimated_weight": "medium",
      "fragility": "moderate"
    },
    {
      "id": "obj_7",
      "label": "medium_object",
      "semantic_category": "container",
      "confidence": 0.95,
      "semantic_confidence": 0.85,
      "bbox_2d": [
        479.0,
        127.0,
        108.0,
        154.0
      ],
      "bbox_3d": {
        "center": [
          533.0,
          204.0,
          1.0
        ],
        "dimensions": [
          0.108,
          0.154,
          0.1
        ],
        "min_bounds": [
          479.0,
          127.0,
          0.95
        ],
        "max_bounds": [
          587.0,
          281.0,
          1.05
        ]
      },
      "center_2d": [
        533.0,
        204.0
      ],
      "center_3d": [
        533.0,
        204.0,
        1.0
      ],
      "affordances": [
        "graspable",
        "holdable",
        "drinkable"
      ],
      "description": "drinking vessel",
      "num_grasps": 5,
      "best_grasp_quality": 0.6184485459675527,
      "graspable": true,
      "best_grasp": {
        "object_id": 3,
        "object_label": "medium_object",
        "pose": {
          "position": [
            "0.1974684",
            "0.011161121",
            "0.40588048"
          ],
          "approach_vector": [
            0.5763708598541113,
            0.7933064309896235,
            -0.19611613513818407
          ],
          "rotation_matrix": "[[   -0.80902     0.58779           0]\n [   -0.58779    -0.80902           0]\n [          0           0           1]]",
          "angle": 3.7699111843077517,
          "quaternion": [
            1.0,
            0.0,
            0.0,
            0.0
          ]
        },
        "quality_score": 0.6184485459675527,
        "gripper_width": 0.08,
        "approach_vector": [
          0.5763708598541113,
          0.7933064309896235,
          -0.19611613513818407
        ],
        "grasp_center": [
          "0.16864985",
          "-0.028504202",
          "0.41568628"
        ],
        "confidence": 0.587526118669175
      },
      "estimated_size": 0.54140625,
      "estimated_weight": "medium",
      "fragility": "moderate"
    },
    {
      "id": "obj_8",
      "label": "small_object",
      "semantic_category": "electronics",
      "confidence": 0.6295712671458643,
      "semantic_confidence": 0.85,
      "bbox_2d": [
        111,
        160,
        69,
        83
      ],
      "bbox_3d": {
        "center": [
          145.5,
          201.5,
          1.0
        ],
        "dimensions": [
          0.069,
          0.083,
          0.1
        ],
        "min_bounds": [
          111,
          160,
          0.95
        ],
        "max_bounds": [
          180,
          243,
          1.05
        ]
      },
      "center_2d": [
        145,
        201
      ],
      "center_3d": [
        145.5,
        201.5,
        1.0
      ],
      "affordances": [
        "usable",
        "pressable",
        "typing"
      ],
      "description": "computer input device",
      "num_grasps": 10,
      "best_grasp_quality": 0.4040490959842078,
      "graspable": true,
      "best_grasp": {
        "object_id": 3,
        "object_label": "small_object",
        "pose": {
          "position": [
            "-0.1907893",
            "-0.009275854",
            "0.64901775"
          ],
          "approach_vector": [
            0.5763708598541113,
            0.7933064309896235,
            -0.19611613513818407
          ],
          "rotation_matrix": "[[   -0.80902     0.58779           0]\n [   -0.58779    -0.80902           0]\n [          0           0           1]]",
          "angle": 3.7699111843077517,
          "quaternion": [
            1.0,
            0.0,
            0.0,
            0.0
          ]
        },
        "quality_score": 0.4040490959842078,
        "gripper_width": 0.08,
        "approach_vector": [
          0.5763708598541113,
          0.7933064309896235,
          -0.19611613513818407
        ],
        "grasp_center": [
          "-0.21960784",
          "-0.048941176",
          "0.65882355"
        ],
        "confidence": 0.25437770134791865
      },
      "estimated_size": 0.18642578125,
      "estimated_weight": "medium",
      "fragility": "moderate"
    }
  ],
  "edges": [
    {
      "id": "rel_0",
      "subject": {
        "id": "obj_0",
        "label": "elongated_large_object"
      },
      "object": {
        "id": "obj_1",
        "label": "large_object"
      },
      "relation": "right_of",
      "confidence": 0.8,
      "description": "elongated_large_object right_of large_object"
    },
    {
      "id": "rel_1",
      "subject": {
        "id": "obj_0",
        "label": "elongated_large_object"
      },
      "object": {
        "id": "obj_1",
        "label": "large_object"
      },
      "relation": "below",
      "confidence": 0.8,
      "description": "elongated_large_object below large_object"
    },
    {
      "id": "rel_2",
      "subject": {
        "id": "obj_0",
        "label": "elongated_large_object"
      },
      "object": {
        "id": "obj_1",
        "label": "large_object"
      },
      "relation": "overlapping",
      "confidence": 0.5381139775542924,
      "description": "elongated_large_object overlapping large_object"
    },
    {
      "id": "rel_3",
      "subject": {
        "id": "obj_0",
        "label": "elongated_large_object"
      },
      "object": {
        "id": "obj_2",
        "label": "large_object"
      },
      "relation": "right_of",
      "confidence": 0.8,
      "description": "elongated_large_object right_of large_object"
    },
    {
      "id": "rel_4",
      "subject": {
        "id": "obj_0",
        "label": "elongated_large_object"
      },
      "object": {
        "id": "obj_2",
        "label": "large_object"
      },
      "relation": "near",
      "confidence": 0.9,
      "description": "elongated_large_object near large_object"
    },
    {
      "id": "rel_5",
      "subject": {
        "id": "obj_0",
        "label": "elongated_large_object"
      },
      "object": {
        "id": "obj_2",
        "label": "large_object"
      },
      "relation": "overlapping",
      "confidence": 0.5562179277213669,
      "description": "elongated_large_object overlapping large_object"
    },
    {
      "id": "rel_6",
      "subject": {
        "id": "obj_0",
        "label": "elongated_large_object"
      },
      "object": {
        "id": "obj_3",
        "label": "elongated_large_object"
      },
      "relation": "left_of",
      "confidence": 0.8,
      "description": "elongated_large_object left_of elongated_large_object"
    },
    {
      "id": "rel_7",
      "subject": {
        "id": "obj_0",
        "label": "elongated_large_object"
      },
      "object": {
        "id": "obj_3",
        "label": "elongated_large_object"
      },
      "relation": "below",
      "confidence": 0.8,
      "description": "elongated_large_object below elongated_large_object"
    },
    {
      "id": "rel_8",
      "subject": {
        "id": "obj_0",
        "label": "elongated_large_object"
      },
      "object": {
        "id": "obj_4",
        "label": "small_object"
      },
      "relation": "left_of",
      "confidence": 0.8,
      "description": "elongated_large_object left_of small_object"
    },
    {
      "id": "rel_9",
      "subject": {
        "id": "obj_0",
        "label": "elongated_large_object"
      },
      "object": {
        "id": "obj_4",
        "label": "small_object"
      },
      "relation": "below",
      "confidence": 0.8,
      "description": "elongated_large_object below small_object"
    },
    {
      "id": "rel_10",
      "subject": {
        "id": "obj_0",
        "label": "elongated_large_object"
      },
      "object": {
        "id": "obj_4",
        "label": "small_object"
      },
      "relation": "near",
      "confidence": 0.9,
      "description": "elongated_large_object near small_object"
    },
    {
      "id": "rel_11",
      "subject": {
        "id": "obj_0",
        "label": "elongated_large_object"
      },
      "object": {
        "id": "obj_5",
        "label": "large_object"
      },
      "relation": "left_of",
      "confidence": 0.8,
      "description": "elongated_large_object left_of large_object"
    },
    {
      "id": "rel_12",
      "subject": {
        "id": "obj_0",
        "label": "elongated_large_object"
      },
      "object": {
        "id": "obj_5",
        "label": "large_object"
      },
      "relation": "below",
      "confidence": 0.8,
      "description": "elongated_large_object below large_object"
    },
    {
      "id": "rel_13",
      "subject": {
        "id": "obj_0",
        "label": "elongated_large_object"
      },
      "object": {
        "id": "obj_5",
        "label": "large_object"
      },
      "relation": "near",
      "confidence": 0.9,
      "description": "elongated_large_object near large_object"
    },
    {
      "id": "rel_14",
      "subject": {
        "id": "obj_0",
        "label": "elongated_large_object"
      },
      "object": {
        "id": "obj_5",
        "label": "large_object"
      },
      "relation": "overlapping",
      "confidence": 0.7718602922962596,
      "description": "elongated_large_object overlapping large_object"
    },
    {
      "id": "rel_15",
      "subject": {
        "id": "obj_0",
        "label": "elongated_large_object"
      },
      "object": {
        "id": "obj_6",
        "label": "elongated_large_object"
      },
      "relation": "left_of",
      "confidence": 0.8,
      "description": "elongated_large_object left_of elongated_large_object"
    },
    {
      "id": "rel_16",
      "subject": {
        "id": "obj_0",
        "label": "elongated_large_object"
      },
      "object": {
        "id": "obj_6",
        "label": "elongated_large_object"
      },
      "relation": "below",
      "confidence": 0.8,
      "description": "elongated_large_object below elongated_large_object"
    },
    {
      "id": "rel_17",
      "subject": {
        "id": "obj_0",
        "label": "elongated_large_object"
      },
      "object": {
        "id": "obj_6",
        "label": "elongated_large_object"
      },
      "relation": "near",
      "confidence": 0.9,
      "description": "elongated_large_object near elongated_large_object"
    },
    {
      "id": "rel_18",
      "subject": {
        "id": "obj_0",
        "label": "elongated_large_object"
      },
      "object": {
        "id": "obj_6",
        "label": "elongated_large_object"
      },
      "relation": "overlapping",
      "confidence": 0.8981475415802307,
      "description": "elongated_large_object overlapping elongated_large_object"
    },
    {
      "id": "rel_19",
      "subject": {
        "id": "obj_0",
        "label": "elongated_large_object"
      },
      "object": {
        "id": "obj_7",
        "label": "medium_object"
      },
      "relation": "left_of",
      "confidence": 0.8,
      "description": "elongated_large_object left_of medium_object"
    },
    {
      "id": "rel_20",
      "subject": {
        "id": "obj_0",
        "label": "elongated_large_object"
      },
      "object": {
        "id": "obj_7",
        "label": "medium_object"
      },
      "relation": "overlapping",
      "confidence": 0.24212250245660005,
      "description": "elongated_large_object overlapping medium_object"
    },
    {
      "id": "rel_21",
      "subject": {
        "id": "obj_0",
        "label": "elongated_large_object"
      },
      "object": {
        "id": "obj_8",
        "label": "small_object"
      },
      "relation": "right_of",
      "confidence": 0.8,
      "description": "elongated_large_object right_of small_object"
    },
    {
      "id": "rel_22",
      "subject": {
        "id": "obj_1",
        "label": "large_object"
      },
      "object": {
        "id": "obj_2",
        "label": "large_object"
      },
      "relation": "left_of",
      "confidence": 0.8,
      "description": "large_object left_of large_object"
    },
    {
      "id": "rel_23",
      "subject": {
        "id": "obj_1",
        "label": "large_object"
      },
      "object": {
        "id": "obj_2",
        "label": "large_object"
      },
      "relation": "above",
      "confidence": 0.8,
      "description": "large_object above large_object"
    },
    {
      "id": "rel_24",
      "subject": {
        "id": "obj_1",
        "label": "large_object"
      },
      "object": {
        "id": "obj_2",
        "label": "large_object"
      },
      "relation": "overlapping",
      "confidence": 0.2081192240781151,
      "description": "large_object overlapping large_object"
    },
    {
      "id": "rel_25",
      "subject": {
        "id": "obj_1",
        "label": "large_object"
      },
      "object": {
        "id": "obj_3",
        "label": "elongated_large_object"
      },
      "relation": "left_of",
      "confidence": 0.8,
      "description": "large_object left_of elongated_large_object"
    },
    {
      "id": "rel_26",
      "subject": {
        "id": "obj_1",
        "label": "large_object"
      },
      "object": {
        "id": "obj_3",
        "label": "elongated_large_object"
      },
      "relation": "below",
      "confidence": 0.8,
      "description": "large_object below elongated_large_object"
    },
    {
      "id": "rel_27",
      "subject": {
        "id": "obj_1",
        "label": "large_object"
      },
      "object": {
        "id": "obj_4",
        "label": "small_object"
      },
      "relation": "left_of",
      "confidence": 0.8,
      "description": "large_object left_of small_object"
    },
    {
      "id": "rel_28",
      "subject": {
        "id": "obj_1",
        "label": "large_object"
      },
      "object": {
        "id": "obj_4",
        "label": "small_object"
      },
      "relation": "below",
      "confidence": 0.8,
      "description": "large_object below small_object"
    },
    {
      "id": "rel_29",
      "subject": {
        "id": "obj_1",
        "label": "large_object"
      },
      "object": {
        "id": "obj_5",
        "label": "large_object"
      },
      "relation": "left_of",
      "confidence": 0.8,
      "description": "large_object left_of large_object"
    },
    {
      "id": "rel_30",
      "subject": {
        "id": "obj_1",
        "label": "large_object"
      },
      "object": {
        "id": "obj_5",
        "label": "large_object"
      },
      "relation": "below",
      "confidence": 0.8,
      "description": "large_object below large_object"
    },
    {
      "id": "rel_31",
      "subject": {
        "id": "obj_1",
        "label": "large_object"
      },
      "object": {
        "id": "obj_6",
        "label": "elongated_large_object"
      },
      "relation": "left_of",
      "confidence": 0.8,
      "description": "large_object left_of elongated_large_object"
    },
    {
      "id": "rel_32",
      "subject": {
        "id": "obj_1",
        "label": "large_object"
      },
      "object": {
        "id": "obj_7",
        "label": "medium_object"
      },
      "relation": "left_of",
      "confidence": 0.8,
      "description": "large_object left_of medium_object"
    },
    {
      "id": "rel_33",
      "subject": {
        "id": "obj_1",
        "label": "large_object"
      },
      "object": {
        "id": "obj_7",
        "label": "medium_object"
      },
      "relation": "above",
      "confidence": 0.8,
      "description": "large_object above medium_object"
    },
    {
      "id": "rel_34",
      "subject": {
        "id": "obj_1",
        "label": "large_object"
      },
      "object": {
        "id": "obj_7",
        "label": "medium_object"
      },
      "relation": "far_from",
      "confidence": 0.7,
      "description": "large_object far_from medium_object"
    },
    {
      "id": "rel_35",
      "subject": {
        "id": "obj_1",
        "label": "large_object"
      },
      "object": {
        "id": "obj_8",
        "label": "small_object"
      },
      "relation": "left_of",
      "confidence": 0.8,
      "description": "large_object left_of small_object"
    },
    {
      "id": "rel_36",
      "subject": {
        "id": "obj_1",
        "label": "large_object"
      },
      "object": {
        "id": "obj_8",
        "label": "small_object"
      },
      "relation": "above",
      "confidence": 0.8,
      "description": "large_object above small_object"
    },
    {
      "id": "rel_37",
      "subject": {
        "id": "obj_1",
        "label": "large_object"
      },
      "object": {
        "id": "obj_8",
        "label": "small_object"
      },
      "relation": "near",
      "confidence": 0.9,
      "description": "large_object near small_object"
    },
    {
      "id": "rel_38",
      "subject": {
        "id": "obj_1",
        "label": "large_object"
      },
      "object": {
        "id": "obj_8",
        "label": "small_object"
      },
      "relation": "touching",
      "confidence": 0.6,
      "description": "large_object touching small_object"
    },
    {
      "id": "rel_39",
      "subject": {
        "id": "obj_2",
        "label": "large_object"
      },
      "object": {
        "id": "obj_3",
        "label": "elongated_large_object"
      },
      "relation": "left_of",
      "confidence": 0.8,
      "description": "large_object left_of elongated_large_object"
    },
    {
      "id": "rel_40",
      "subject": {
        "id": "obj_2",
        "label": "large_object"
      },
      "object": {
        "id": "obj_3",
        "label": "elongated_large_object"
      },
      "relation": "below",
      "confidence": 0.8,
      "description": "large_object below elongated_large_object"
    },
    {
      "id": "rel_41",
      "subject": {
        "id": "obj_2",
        "label": "large_object"
      },
      "object": {
        "id": "obj_4",
        "label": "small_object"
      },
      "relation": "left_of",
      "confidence": 0.8,
      "description": "large_object left_of small_object"
    },
    {
      "id": "rel_42",
      "subject": {
        "id": "obj_2",
        "label": "large_object"
      },
      "object": {
        "id": "obj_4",
        "label": "small_object"
      },
      "relation": "below",
      "confidence": 0.8,
      "description": "large_object below small_object"
    },
    {
      "id": "rel_43",
      "subject": {
        "id": "obj_2",
        "label": "large_object"
      },
      "object": {
        "id": "obj_4",
        "label": "small_object"
      },
      "relation": "near",
      "confidence": 0.9,
      "description": "large_object near small_object"
    },
    {
      "id": "rel_44",
      "subject": {
        "id": "obj_2",
        "label": "large_object"
      },
      "object": {
        "id": "obj_5",
        "label": "large_object"
      },
      "relation": "left_of",
      "confidence": 0.8,
      "description": "large_object left_of large_object"
    },
    {
      "id": "rel_45",
      "subject": {
        "id": "obj_2",
        "label": "large_object"
      },
      "object": {
        "id": "obj_5",
        "label": "large_object"
      },
      "relation": "below",
      "confidence": 0.8,
      "description": "large_object below large_object"
    },
    {
      "id": "rel_46",
      "subject": {
        "id": "obj_2",
        "label": "large_object"
      },
      "object": {
        "id": "obj_5",
        "label": "large_object"
      },
      "relation": "overlapping",
      "confidence": 0.26310832956390845,
      "description": "large_object overlapping large_object"
    },
    {
      "id": "rel_47",
      "subject": {
        "id": "obj_2",
        "label": "large_object"
      },
      "object": {
        "id": "obj_6",
        "label": "elongated_large_object"
      },
      "relation": "left_of",
      "confidence": 0.8,
      "description": "large_object left_of elongated_large_object"
    },
    {
      "id": "rel_48",
      "subject": {
        "id": "obj_2",
        "label": "large_object"
      },
      "object": {
        "id": "obj_6",
        "label": "elongated_large_object"
      },
      "relation": "below",
      "confidence": 0.8,
      "description": "large_object below elongated_large_object"
    },
    {
      "id": "rel_49",
      "subject": {
        "id": "obj_2",
        "label": "large_object"
      },
      "object": {
        "id": "obj_6",
        "label": "elongated_large_object"
      },
      "relation": "overlapping",
      "confidence": 0.5837018646390979,
      "description": "large_object overlapping elongated_large_object"
    },
    {
      "id": "rel_50",
      "subject": {
        "id": "obj_2",
        "label": "large_object"
      },
      "object": {
        "id": "obj_7",
        "label": "medium_object"
      },
      "relation": "left_of",
      "confidence": 0.8,
      "description": "large_object left_of medium_object"
    },
    {
      "id": "rel_51",
      "subject": {
        "id": "obj_2",
        "label": "large_object"
      },
      "object": {
        "id": "obj_8",
        "label": "small_object"
      },
      "relation": "right_of",
      "confidence": 0.8,
      "description": "large_object right_of small_object"
    },
    {
      "id": "rel_52",
      "subject": {
        "id": "obj_2",
        "label": "large_object"
      },
      "object": {
        "id": "obj_8",
        "label": "small_object"
      },
      "relation": "near",
      "confidence": 0.9,
      "description": "large_object near small_object"
    },
    {
      "id": "rel_53",
      "subject": {
        "id": "obj_3",
        "label": "elongated_large_object"
      },
      "object": {
        "id": "obj_4",
        "label": "small_object"
      },
      "relation": "right_of",
      "confidence": 0.8,
      "description": "elongated_large_object right_of small_object"
    },
    {
      "id": "rel_54",
      "subject": {
        "id": "obj_3",
        "label": "elongated_large_object"
      },
      "object": {
        "id": "obj_4",
        "label": "small_object"
      },
      "relation": "above",
      "confidence": 0.8,
      "description": "elongated_large_object above small_object"
    },
    {
      "id": "rel_55",
      "subject": {
        "id": "obj_3",
        "label": "elongated_large_object"
      },
      "object": {
        "id": "obj_4",
        "label": "small_object"
      },
      "relation": "near",
      "confidence": 0.9,
      "description": "elongated_large_object near small_object"
    },
    {
      "id": "rel_56",
      "subject": {
        "id": "obj_3",
        "label": "elongated_large_object"
      },
      "object": {
        "id": "obj_4",
        "label": "small_object"
      },
      "relation": "touching",
      "confidence": 0.6,
      "description": "elongated_large_object touching small_object"
    },
    {
      "id": "rel_57",
      "subject": {
        "id": "obj_3",
        "label": "elongated_large_object"
      },
      "object": {
        "id": "obj_5",
        "label": "large_object"
      },
      "relation": "above",
      "confidence": 0.8,
      "description": "elongated_large_object above large_object"
    },
    {
      "id": "rel_58",
      "subject": {
        "id": "obj_3",
        "label": "elongated_large_object"
      },
      "object": {
        "id": "obj_5",
        "label": "large_object"
      },
      "relation": "near",
      "confidence": 0.9,
      "description": "elongated_large_object near large_object"
    },
    {
      "id": "rel_59",
      "subject": {
        "id": "obj_3",
        "label": "elongated_large_object"
      },
      "object": {
        "id": "obj_5",
        "label": "large_object"
      },
      "relation": "overlapping",
      "confidence": 0.8330184956636358,
      "description": "elongated_large_object overlapping large_object"
    },
    {
      "id": "rel_60",
      "subject": {
        "id": "obj_3",
        "label": "elongated_large_object"
      },
      "object": {
        "id": "obj_6",
        "label": "elongated_large_object"
      },
      "relation": "above",
      "confidence": 0.8,
      "description": "elongated_large_object above elongated_large_object"
    },
    {
      "id": "rel_61",
      "subject": {
        "id": "obj_3",
        "label": "elongated_large_object"
      },
      "object": {
        "id": "obj_6",
        "label": "elongated_large_object"
      },
      "relation": "near",
      "confidence": 0.9,
      "description": "elongated_large_object near elongated_large_object"
    },
    {
      "id": "rel_62",
      "subject": {
        "id": "obj_3",
        "label": "elongated_large_object"
      },
      "object": {
        "id": "obj_7",
        "label": "medium_object"
      },
      "relation": "left_of",
      "confidence": 0.8,
      "description": "elongated_large_object left_of medium_object"
    },
    {
      "id": "rel_63",
      "subject": {
        "id": "obj_3",
        "label": "elongated_large_object"
      },
      "object": {
        "id": "obj_7",
        "label": "medium_object"
      },
      "relation": "above",
      "confidence": 0.8,
      "description": "elongated_large_object above medium_object"
    },
    {
      "id": "rel_64",
      "subject": {
        "id": "obj_3",
        "label": "elongated_large_object"
      },
      "object": {
        "id": "obj_8",
        "label": "small_object"
      },
      "relation": "right_of",
      "confidence": 0.8,
      "description": "elongated_large_object right_of small_object"
    },
    {
      "id": "rel_65",
      "subject": {
        "id": "obj_3",
        "label": "elongated_large_object"
      },
      "object": {
        "id": "obj_8",
        "label": "small_object"
      },
      "relation": "above",
      "confidence": 0.8,
      "description": "elongated_large_object above small_object"
    },
    {
      "id": "rel_66",
      "subject": {
        "id": "obj_4",
        "label": "small_object"
      },
      "object": {
        "id": "obj_5",
        "label": "large_object"
      },
      "relation": "left_of",
      "confidence": 0.8,
      "description": "small_object left_of large_object"
    },
    {
      "id": "rel_67",
      "subject": {
        "id": "obj_4",
        "label": "small_object"
      },
      "object": {
        "id": "obj_5",
        "label": "large_object"
      },
      "relation": "near",
      "confidence": 0.9,
      "description": "small_object near large_object"
    },
    {
      "id": "rel_68",
      "subject": {
        "id": "obj_4",
        "label": "small_object"
      },
      "object": {
        "id": "obj_5",
        "label": "large_object"
      },
      "relation": "touching",
      "confidence": 0.6,
      "description": "small_object touching large_object"
    },
    {
      "id": "rel_69",
      "subject": {
        "id": "obj_4",
        "label": "small_object"
      },
      "object": {
        "id": "obj_6",
        "label": "elongated_large_object"
      },
      "relation": "left_of",
      "confidence": 0.8,
      "description": "small_object left_of elongated_large_object"
    },
    {
      "id": "rel_70",
      "subject": {
        "id": "obj_4",
        "label": "small_object"
      },
      "object": {
        "id": "obj_6",
        "label": "elongated_large_object"
      },
      "relation": "above",
      "confidence": 0.8,
      "description": "small_object above elongated_large_object"
    },
    {
      "id": "rel_71",
      "subject": {
        "id": "obj_4",
        "label": "small_object"
      },
      "object": {
        "id": "obj_6",
        "label": "elongated_large_object"
      },
      "relation": "near",
      "confidence": 0.9,
      "description": "small_object near elongated_large_object"
    },
    {
      "id": "rel_72",
      "subject": {
        "id": "obj_4",
        "label": "small_object"
      },
      "object": {
        "id": "obj_6",
        "label": "elongated_large_object"
      },
      "relation": "touching",
      "confidence": 0.6,
      "description": "small_object touching elongated_large_object"
    },
    {
      "id": "rel_73",
      "subject": {
        "id": "obj_4",
        "label": "small_object"
      },
      "object": {
        "id": "obj_7",
        "label": "medium_object"
      },
      "relation": "left_of",
      "confidence": 0.8,
      "description": "small_object left_of medium_object"
    },
    {
      "id": "rel_74",
      "subject": {
        "id": "obj_4",
        "label": "small_object"
      },
      "object": {
        "id": "obj_7",
        "label": "medium_object"
      },
      "relation": "above",
      "confidence": 0.8,
      "description": "small_object above medium_object"
    },
    {
      "id": "rel_75",
      "subject": {
        "id": "obj_4",
        "label": "small_object"
      },
      "object": {
        "id": "obj_8",
        "label": "small_object"
      },
      "relation": "right_of",
      "confidence": 0.8,
      "description": "small_object right_of small_object"
    },
    {
      "id": "rel_76",
      "subject": {
        "id": "obj_4",
        "label": "small_object"
      },
      "object": {
        "id": "obj_8",
        "label": "small_object"
      },
      "relation": "above",
      "confidence": 0.8,
      "description": "small_object above small_object"
    },
    {
      "id": "rel_77",
      "subject": {
        "id": "obj_5",
        "label": "large_object"
      },
      "object": {
        "id": "obj_6",
        "label": "elongated_large_object"
      },
      "relation": "right_of",
      "confidence": 0.8,
      "description": "large_object right_of elongated_large_object"
    },
    {
      "id": "rel_78",
      "subject": {
        "id": "obj_5",
        "label": "large_object"
      },
      "object": {
        "id": "obj_6",
        "label": "elongated_large_object"
      },
      "relation": "above",
      "confidence": 0.8,
      "description": "large_object above elongated_large_object"
    },
    {
      "id": "rel_79",
      "subject": {
        "id": "obj_5",
        "label": "large_object"
      },
      "object": {
        "id": "obj_6",
        "label": "elongated_large_object"
      },
      "relation": "near",
      "confidence": 0.9,
      "description": "large_object near elongated_large_object"
    },
    {
      "id": "rel_80",
      "subject": {
        "id": "obj_5",
        "label": "large_object"
      },
      "object": {
        "id": "obj_6",
        "label": "elongated_large_object"
      },
      "relation": "overlapping",
      "confidence": 0.8491497176512467,
      "description": "large_object overlapping elongated_large_object"
    },
    {
      "id": "rel_81",
      "subject": {
        "id": "obj_5",
        "label": "large_object"
      },
      "object": {
        "id": "obj_7",
        "label": "medium_object"
      },
      "relation": "left_of",
      "confidence": 0.8,
      "description": "large_object left_of medium_object"
    },
    {
      "id": "rel_82",
      "subject": {
        "id": "obj_5",
        "label": "large_object"
      },
      "object": {
        "id": "obj_7",
        "label": "medium_object"
      },
      "relation": "above",
      "confidence": 0.8,
      "description": "large_object above medium_object"
    },
    {
      "id": "rel_83",
      "subject": {
        "id": "obj_5",
        "label": "large_object"
      },
      "object": {
        "id": "obj_7",
        "label": "medium_object"
      },
      "relation": "near",
      "confidence": 0.9,
      "description": "large_object near medium_object"
    },
    {
      "id": "rel_84",
      "subject": {
        "id": "obj_5",
        "label": "large_object"
      },
      "object": {
        "id": "obj_7",
        "label": "medium_object"
      },
      "relation": "overlapping",
      "confidence": 0.28647714779330924,
      "description": "large_object overlapping medium_object"
    },
    {
      "id": "rel_85",
      "subject": {
        "id": "obj_5",
        "label": "large_object"
      },
      "object": {
        "id": "obj_8",
        "label": "small_object"
      },
      "relation": "right_of",
      "confidence": 0.8,
      "description": "large_object right_of small_object"
    },
    {
      "id": "rel_86",
      "subject": {
        "id": "obj_5",
        "label": "large_object"
      },
      "object": {
        "id": "obj_8",
        "label": "small_object"
      },
      "relation": "above",
      "confidence": 0.8,
      "description": "large_object above small_object"
    },
    {
      "id": "rel_87",
      "subject": {
        "id": "obj_6",
        "label": "elongated_large_object"
      },
      "object": {
        "id": "obj_7",
        "label": "medium_object"
      },
      "relation": "left_of",
      "confidence": 0.8,
      "description": "elongated_large_object left_of medium_object"
    },
    {
      "id": "rel_88",
      "subject": {
        "id": "obj_6",
        "label": "elongated_large_object"
      },
      "object": {
        "id": "obj_7",
        "label": "medium_object"
      },
      "relation": "above",
      "confidence": 0.8,
      "description": "elongated_large_object above medium_object"
    },
    {
      "id": "rel_89",
      "subject": {
        "id": "obj_6",
        "label": "elongated_large_object"
      },
      "object": {
        "id": "obj_7",
        "label": "medium_object"
      },
      "relation": "near",
      "confidence": 0.9,
      "description": "elongated_large_object near medium_object"
    },
    {
      "id": "rel_90",
      "subject": {
        "id": "obj_6",
        "label": "elongated_large_object"
      },
      "object": {
        "id": "obj_7",
        "label": "medium_object"
      },
      "relation": "overlapping",
      "confidence": 0.38470437800645435,
      "description": "elongated_large_object overlapping medium_object"
    },
    {
      "id": "rel_91",
      "subject": {
        "id": "obj_6",
        "label": "elongated_large_object"
      },
      "object": {
        "id": "obj_8",
        "label": "small_object"
      },
      "relation": "right_of",
      "confidence": 0.8,
      "description": "elongated_large_object right_of small_object"
    },
    {
      "id": "rel_92",
      "subject": {
        "id": "obj_6",
        "label": "elongated_large_object"
      },
      "object": {
        "id": "obj_8",
        "label": "small_object"
      },
      "relation": "above",
      "confidence": 0.8,
      "description": "elongated_large_object above small_object"
    },
    {
      "id": "rel_93",
      "subject": {
        "id": "obj_7",
        "label": "medium_object"
      },
      "object": {
        "id": "obj_8",
        "label": "small_object"
      },
      "relation": "right_of",
      "confidence": 0.8,
      "description": "medium_object right_of small_object"
    },
    {
      "id": "rel_94",
      "subject": {
        "id": "obj_7",
        "label": "medium_object"
      },
      "object": {
        "id": "obj_8",
        "label": "small_object"
      },
      "relation": "far_from",
      "confidence": 0.7,
      "description": "medium_object far_from small_object"
    }
  ],
  "scene_properties": {
    "object_statistics": {
      "total_objects": 9,
      "unique_labels": 4,
      "object_counts": {
        "elongated_large_object": 3,
        "large_object": 3,
        "small_object": 2,
        "medium_object": 1
      },
      "category_counts": {
        "document": 3,
        "container": 4,
        "electronics": 2
      },
      "affordance_counts": {
        "readable": 3,
        "openable": 3,
        "portable": 3,
        "graspable": 4,
        "holdable": 4,
        "drinkable": 4,
        "usable": 2,
        "pressable": 2,
        "typing": 2
      }
    },
    "grasp_statistics": {
      "graspable_objects": 9,
      "avg_grasp_quality": 0.6145192799879319,
      "grasp_success_rate": 1.0
    },
    "relation_statistics": {
      "total_relations": 95,
      "relation_counts": {
        "right_of": 11,
        "below": 12,
        "overlapping": 12,
        "near": 15,
        "left_of": 23,
        "above": 16,
        "far_from": 2,
        "touching": 4
      },
      "relation_density": 10.555555555555555
    },
    "scene_complexity": {
      "object_density": 0.29296875,
      "relation_density": 10.555555555555555,
      "complexity_score": 5.424262152777778
    }
  },
  "semantic_groups": {
    "by_category": {
      "document": [
        "obj_0",
        "obj_3",
        "obj_6"
      ],
      "container": [
        "obj_1",
        "obj_2",
        "obj_5",
        "obj_7"
      ],
      "electronics": [
        "obj_4",
        "obj_8"
      ]
    },
    "by_affordance": {
      "readable": [
        "obj_0",
        "obj_3",
        "obj_6"
      ],
      "openable": [
        "obj_0",
        "obj_3",
        "obj_6"
      ],
      "portable": [
        "obj_0",
        "obj_3",
        "obj_6"
      ],
      "graspable": [
        "obj_1",
        "obj_2",
        "obj_5",
        "obj_7"
      ],
      "holdable": [
        "obj_1",
        "obj_2",
        "obj_5",
        "obj_7"
      ],
      "drinkable": [
        "obj_1",
        "obj_2",
        "obj_5",
        "obj_7"
      ],
      "usable": [
        "obj_4",
        "obj_8"
      ],
      "pressable": [
        "obj_4",
        "obj_8"
      ],
      "typing": [
        "obj_4",
        "obj_8"
      ]
    },
    "by_graspability": {
      "graspable": [
        "obj_0",
        "obj_1",
        "obj_2",
        "obj_3",
        "obj_4",
        "obj_5",
        "obj_6",
        "obj_7",
        "obj_8"
      ],
      "not_graspable": []
    },
    "by_size": {
      "small": [
        "obj_4",
        "obj_8"
      ],
      "medium": [
        "obj_7"
      ],
      "large": [
        "obj_0",
        "obj_1",
        "obj_2",
        "obj_3",
        "obj_5",
        "obj_6"
      ]
    }
  },
  "task_insights": {
    "manipulation_candidates": [
      {
        "object_id": "obj_0",
        "label": "elongated_large_object",
        "grasp_quality": 0.6840211303259031,
        "reason": "High grasp quality (0.68) and good accessibility"
      },
      {
        "object_id": "obj_1",
        "label": "large_object",
        "grasp_quality": 0.6840211303259031,
        "reason": "High grasp quality (0.68) and good accessibility"
      },
      {
        "object_id": "obj_2",
        "label": "large_object",
        "grasp_quality": 0.6840211303259031,
        "reason": "High grasp quality (0.68) and good accessibility"
      }
    ],
    "spatial_constraints": [
      {
        "constraint_type": "overlapping",
        "description": "elongated_large_object overlapping large_object",
        "impact": "Movement of one object affects the other"
      },
      {
        "constraint_type": "overlapping",
        "description": "elongated_large_object overlapping large_object",
        "impact": "Movement of one object affects the other"
      },
      {
        "constraint_type": "overlapping",
        "description": "elongated_large_object overlapping large_object",
        "impact": "Movement of one object affects the other"
      },
      {
        "constraint_type": "overlapping",
        "description": "elongated_large_object overlapping elongated_large_object",
        "impact": "Movement of one object affects the other"
      },
      {
        "constraint_type": "overlapping",
        "description": "elongated_large_object overlapping medium_object",
        "impact": "Movement of one object affects the other"
      },
      {
        "constraint_type": "overlapping",
        "description": "large_object overlapping large_object",
        "impact": "Movement of one object affects the other"
      },
      {
        "constraint_type": "touching",
        "description": "large_object touching small_object",
        "impact": "Movement of one object affects the other"
      },
      {
        "constraint_type": "overlapping",
        "description": "large_object overlapping large_object",
        "impact": "Movement of one object affects the other"
      },
      {
        "constraint_type": "overlapping",
        "description": "large_object overlapping elongated_large_object",
        "impact": "Movement of one object affects the other"
      },
      {
        "constraint_type": "touching",
        "description": "elongated_large_object touching small_object",
        "impact": "Movement of one object affects the other"
      },
      {
        "constraint_type": "overlapping",
        "description": "elongated_large_object overlapping large_object",
        "impact": "Movement of one object affects the other"
      },
      {
        "constraint_type": "touching",
        "description": "small_object touching large_object",
        "impact": "Movement of one object affects the other"
      },
      {
        "constraint_type": "touching",
        "description": "small_object touching elongated_large_object",
        "impact": "Movement of one object affects the other"
      },
      {
        "constraint_type": "overlapping",
        "description": "large_object overlapping elongated_large_object",
        "impact": "Movement of one object affects the other"
      },
      {
        "constraint_type": "overlapping",
        "description": "large_object overlapping medium_object",
        "impact": "Movement of one object affects the other"
      },
      {
        "constraint_type": "overlapping",
        "description": "elongated_large_object overlapping medium_object",
        "impact": "Movement of one object affects the other"
      }
    ],
    "task_recommendations": [
      {
        "task": "pouring",
        "objects": [
          "obj_1",
          "obj_2",
          "obj_5",
          "obj_7"
        ],
        "feasibility": "high"
      }
    ],
    "potential_actions": [
      {
        "object_id": "obj_0",
        "label": "elongated_large_object",
        "actions": [
          "pick",
          "move",
          "open"
        ]
      },
      {
        "object_id": "obj_1",
        "label": "large_object",
        "actions": [
          "pick",
          "move"
        ]
      },
      {
        "object_id": "obj_2",
        "label": "large_object",
        "actions": [
          "pick",
          "move"
        ]
      },
      {
        "object_id": "obj_3",
        "label": "elongated_large_object",
        "actions": [
          "pick",
          "move",
          "open"
        ]
      },
      {
        "object_id": "obj_5",
        "label": "large_object",
        "actions": [
          "pick",
          "move"
        ]
      },
      {
        "object_id": "obj_6",
        "label": "elongated_large_object",
        "actions": [
          "pick",
          "move",
          "open"
        ]
      },
      {
        "object_id": "obj_7",
        "label": "medium_object",
        "actions": [
          "pick",
          "move"
        ]
      },
      {
        "object_id": "obj_4",
        "label": "small_object",
        "actions": [
          "pick",
          "move",
          "use"
        ]
      },
      {
        "object_id": "obj_8",
        "label": "small_object",
        "actions": [
          "pick",
          "move",
          "use"
        ]
      }
    ]
  },
  "grasp_summary": {
    "total_grasps": 45,
    "avg_quality": 0.5645967936989321,
    "max_quality": 0.6840211303259031,
    "min_quality": 0.3264369214240707,
    "high_quality_grasps": 0,
    "objects_with_grasps": 4
  }
}